image_analyst/hf/__init__.py
image_analyst/hf/models.py
image_analyst_hf-0.2.0.dist-info/LICENSE
image_analyst_hf-0.2.0.dist-info/METADATA
image_analyst_hf-0.2.0.dist-info/WHEEL
image_analyst_hf-0.2.0.dist-info/RECORD
